{
	"info": {
		"_postman_id": "1f3d091d-456b-4ffe-be60-cf2b57aea2f6",
		"name": "Akademi-kampus",
		"schema": "https://schema.getpostman.com/json/collection/v2.1.0/collection.json",
		"_exporter_id": "44304920",
		"_collection_link": "https://molyadi.postman.co/workspace/molyadi's-Workspace~b4713c6c-9045-4181-87e5-0554a152c580/collection/44304920-1f3d091d-456b-4ffe-be60-cf2b57aea2f6?action=share&source=collection_link&creator=44304920"
	},
	"item": [
		{
			"name": "User",
			"item": [
				{
					"name": "Get User",
					"request": {
						"auth": {
							"type": "bearer",
							"bearer": [
								{
									"key": "token",
									"value": "{{token}}",
									"type": "string"
								}
							]
						},
						"method": "GET",
						"header": [],
						"url": {
							"raw": "http://127.0.0.1:8000/api/user",
							"protocol": "http",
							"host": [
								"127",
								"0",
								"0",
								"1"
							],
							"port": "8000",
							"path": [
								"api",
								"user"
							]
						}
					},
					"response": []
				},
				{
					"name": "Get User By Id",
					"request": {
						"auth": {
							"type": "bearer",
							"bearer": [
								{
									"key": "token",
									"value": "{{token}}",
									"type": "string"
								}
							]
						},
						"method": "GET",
						"header": [],
						"url": {
							"raw": "http://127.0.0.1:8000/api/user/",
							"protocol": "http",
							"host": [
								"127",
								"0",
								"0",
								"1"
							],
							"port": "8000",
							"path": [
								"api",
								"user",
								""
							]
						}
					},
					"response": []
				},
				{
					"name": "Create User",
					"request": {
						"auth": {
							"type": "bearer",
							"bearer": [
								{
									"key": "token",
									"value": "{{token}}",
									"type": "string"
								}
							]
						},
						"method": "POST",
						"header": [
							{
								"key": "Accept",
								"value": "application/json",
								"type": "text"
							}
						],
						"body": {
							"mode": "formdata",
							"formdata": [
								{
									"key": "name",
									"value": "ajis",
									"type": "text"
								},
								{
									"key": "username",
									"value": "ajis12",
									"type": "text"
								},
								{
									"key": "email",
									"value": "ajis@gmail.com",
									"type": "text"
								},
								{
									"key": "password",
									"value": "ajis1234",
									"type": "text"
								}
							]
						},
						"url": {
							"raw": "http://127.0.0.1:8000/api/user",
							"protocol": "http",
							"host": [
								"127",
								"0",
								"0",
								"1"
							],
							"port": "8000",
							"path": [
								"api",
								"user"
							]
						}
					},
					"response": []
				},
				{
					"name": "Update User",
					"request": {
						"auth": {
							"type": "bearer",
							"bearer": [
								{
									"key": "token",
									"value": "{{token}}",
									"type": "string"
								}
							]
						},
						"method": "PATCH",
						"header": [],
						"body": {
							"mode": "raw",
							"raw": "{\r\n    \r\n}",
							"options": {
								"raw": {
									"language": "json"
								}
							}
						},
						"url": {
							"raw": "http://127.0.0.1:8000/api/user/",
							"protocol": "http",
							"host": [
								"127",
								"0",
								"0",
								"1"
							],
							"port": "8000",
							"path": [
								"api",
								"user",
								""
							]
						}
					},
					"response": []
				},
				{
					"name": "Hapus User",
					"request": {
						"auth": {
							"type": "bearer",
							"bearer": [
								{
									"key": "token",
									"value": "{{token}}",
									"type": "string"
								}
							]
						},
						"method": "DELETE",
						"header": [],
						"url": {
							"raw": "http://127.0.0.1:8000/api/user/01jw8ngdth8hzppqfss2zwv6xz",
							"protocol": "http",
							"host": [
								"127",
								"0",
								"0",
								"1"
							],
							"port": "8000",
							"path": [
								"api",
								"user",
								"01jw8ngdth8hzppqfss2zwv6xz"
							]
						}
					},
					"response": []
				}
			]
		},
		{
			"name": "Students",
			"item": [
				{
					"name": "Get Students",
					"request": {
						"auth": {
							"type": "bearer",
							"bearer": [
								{
									"key": "token",
									"value": "{{token}}",
									"type": "string"
								}
							]
						},
						"method": "GET",
						"header": [],
						"url": {
							"raw": "http://127.0.0.1:8000/api/students",
							"protocol": "http",
							"host": [
								"127",
								"0",
								"0",
								"1"
							],
							"port": "8000",
							"path": [
								"api",
								"students"
							]
						}
					},
					"response": []
				},
				{
					"name": "Get Students By Id",
					"request": {
						"auth": {
							"type": "bearer",
							"bearer": [
								{
									"key": "token",
									"value": "{{token}}",
									"type": "string"
								}
							]
						},
						"method": "GET",
						"header": [],
						"url": {
							"raw": "http://127.0.0.1:8000/api/students/",
							"protocol": "http",
							"host": [
								"127",
								"0",
								"0",
								"1"
							],
							"port": "8000",
							"path": [
								"api",
								"students",
								""
							]
						}
					},
					"response": []
				},
				{
					"name": "Create Students",
					"request": {
						"auth": {
							"type": "bearer",
							"bearer": [
								{
									"key": "token",
									"value": "{{token}}",
									"type": "string"
								}
							]
						},
						"method": "POST",
						"header": [
							{
								"key": "Accept",
								"value": "application/json",
								"type": "text"
							},
							{
								"key": "Content-Type",
								"value": "application/json",
								"type": "text"
							}
						],
						"body": {
							"mode": "formdata",
							"formdata": [
								{
									"key": "name",
									"value": "ajis",
									"type": "text"
								},
								{
									"key": "email",
									"value": "ajis@gmail.com",
									"type": "text"
								},
								{
									"key": "NIM",
									"value": "2212121",
									"type": "text"
								},
								{
									"key": "major",
									"value": "infromatika",
									"type": "text"
								},
								{
									"key": "enrollment_year",
									"value": "2004-05-04",
									"type": "text"
								}
							]
						},
						"url": {
							"raw": "http://127.0.0.1:8000/api/students",
							"protocol": "http",
							"host": [
								"127",
								"0",
								"0",
								"1"
							],
							"port": "8000",
							"path": [
								"api",
								"students"
							]
						}
					},
					"response": []
				},
				{
					"name": "Update Students",
					"request": {
						"auth": {
							"type": "bearer",
							"bearer": [
								{
									"key": "token",
									"value": "{{token}}",
									"type": "string"
								}
							]
						},
						"method": "PATCH",
						"header": [],
						"body": {
							"mode": "raw",
							"raw": "{\r\n   \r\n}",
							"options": {
								"raw": {
									"language": "json"
								}
							}
						},
						"url": {
							"raw": "http://127.0.0.1:8000/api/students/",
							"protocol": "http",
							"host": [
								"127",
								"0",
								"0",
								"1"
							],
							"port": "8000",
							"path": [
								"api",
								"students",
								""
							]
						}
					},
					"response": []
				},
				{
					"name": "Hapus Students",
					"request": {
						"auth": {
							"type": "bearer",
							"bearer": [
								{
									"key": "token",
									"value": "{{token}}",
									"type": "string"
								}
							]
						},
						"method": "DELETE",
						"header": [],
						"url": {
							"raw": "http://127.0.0.1:8000/api/students/01JWAWJVVDJC5R75P82MHN3F00",
							"protocol": "http",
							"host": [
								"127",
								"0",
								"0",
								"1"
							],
							"port": "8000",
							"path": [
								"api",
								"students",
								"01JWAWJVVDJC5R75P82MHN3F00"
							]
						}
					},
					"response": []
				}
			]
		},
		{
			"name": "Courses",
			"item": [
				{
					"name": "Get Courses",
					"request": {
						"auth": {
							"type": "bearer",
							"bearer": [
								{
									"key": "token",
									"value": "{{token}}",
									"type": "string"
								}
							]
						},
						"method": "GET",
						"header": [],
						"url": {
							"raw": "http://127.0.0.1:8000/api/courses",
							"protocol": "http",
							"host": [
								"127",
								"0",
								"0",
								"1"
							],
							"port": "8000",
							"path": [
								"api",
								"courses"
							]
						}
					},
					"response": []
				},
				{
					"name": "Get Courses By Id",
					"request": {
						"auth": {
							"type": "bearer",
							"bearer": [
								{
									"key": "token",
									"value": "{{token}}",
									"type": "string"
								}
							]
						},
						"method": "GET",
						"header": [],
						"url": {
							"raw": "http://127.0.0.1:8000/api/courses/",
							"protocol": "http",
							"host": [
								"127",
								"0",
								"0",
								"1"
							],
							"port": "8000",
							"path": [
								"api",
								"courses",
								""
							]
						}
					},
					"response": []
				},
				{
					"name": "Create Courses",
					"request": {
						"auth": {
							"type": "bearer",
							"bearer": [
								{
									"key": "token",
									"value": "{{token}}",
									"type": "string"
								}
							]
						},
						"method": "POST",
						"header": [
							{
								"key": "Accept",
								"value": "application/json",
								"type": "text"
							},
							{
								"key": "Content-Type",
								"value": "application/json",
								"type": "text"
							}
						],
						"body": {
							"mode": "formdata",
							"formdata": [
								{
									"key": "name",
									"value": "",
									"type": "text"
								},
								{
									"key": "code",
									"value": "",
									"type": "text"
								},
								{
									"key": "credits",
									"value": "",
									"type": "text"
								},
								{
									"key": "semester",
									"value": "",
									"type": "text"
								}
							]
						},
						"url": {
							"raw": "http://127.0.0.1:8000/api/courses",
							"protocol": "http",
							"host": [
								"127",
								"0",
								"0",
								"1"
							],
							"port": "8000",
							"path": [
								"api",
								"courses"
							]
						}
					},
					"response": []
				},
				{
					"name": "Update Courses",
					"request": {
						"auth": {
							"type": "bearer",
							"bearer": [
								{
									"key": "token",
									"value": "{{token}}",
									"type": "string"
								}
							]
						},
						"method": "PATCH",
						"header": [],
						"body": {
							"mode": "raw",
							"raw": "{\r\n   \r\n}",
							"options": {
								"raw": {
									"language": "json"
								}
							}
						},
						"url": {
							"raw": "http://127.0.0.1:8000/api/courses/",
							"protocol": "http",
							"host": [
								"127",
								"0",
								"0",
								"1"
							],
							"port": "8000",
							"path": [
								"api",
								"courses",
								""
							]
						}
					},
					"response": []
				},
				{
					"name": "Hapus Courses",
					"request": {
						"auth": {
							"type": "bearer",
							"bearer": [
								{
									"key": "token",
									"value": "{{token}}",
									"type": "string"
								}
							]
						},
						"method": "DELETE",
						"header": [],
						"url": {
							"raw": "http://127.0.0.1:8000/api/courses/01JWAXCXPDR656RBTVWXNB4QP5",
							"protocol": "http",
							"host": [
								"127",
								"0",
								"0",
								"1"
							],
							"port": "8000",
							"path": [
								"api",
								"courses",
								"01JWAXCXPDR656RBTVWXNB4QP5"
							]
						}
					},
					"response": []
				}
			]
		},
		{
			"name": "Enrollment",
			"item": [
				{
					"name": "Get Enrollment",
					"request": {
						"auth": {
							"type": "bearer",
							"bearer": [
								{
									"key": "token",
									"value": "{{token}}",
									"type": "string"
								}
							]
						},
						"method": "GET",
						"header": [],
						"url": {
							"raw": "http://127.0.0.1:8000/api/enrollment",
							"protocol": "http",
							"host": [
								"127",
								"0",
								"0",
								"1"
							],
							"port": "8000",
							"path": [
								"api",
								"enrollment"
							]
						}
					},
					"response": []
				},
				{
					"name": "Get Enrollment By Id",
					"request": {
						"auth": {
							"type": "bearer",
							"bearer": [
								{
									"key": "token",
									"value": "{{token}}",
									"type": "string"
								}
							]
						},
						"method": "GET",
						"header": [],
						"url": {
							"raw": "http://127.0.0.1:8000/api/enrollment/",
							"protocol": "http",
							"host": [
								"127",
								"0",
								"0",
								"1"
							],
							"port": "8000",
							"path": [
								"api",
								"enrollment",
								""
							]
						}
					},
					"response": []
				},
				{
					"name": "Create Enrollment",
					"request": {
						"auth": {
							"type": "bearer",
							"bearer": [
								{
									"key": "token",
									"value": "{{token}}",
									"type": "string"
								}
							]
						},
						"method": "POST",
						"header": [
							{
								"key": "Accept",
								"value": "application/json",
								"type": "text"
							}
						],
						"body": {
							"mode": "formdata",
							"formdata": [
								{
									"key": "student_id",
									"value": "01K0TK7KF82QSHW9D0SFG3T7DF",
									"type": "text"
								},
								{
									"key": "course_id",
									"value": "01K0TKS1CTVS0ZNM5H3N5AMPN7",
									"type": "text"
								},
								{
									"key": "grade",
									"value": "212",
									"type": "text"
								},
								{
									"key": "attendance",
									"value": "1212",
									"type": "text"
								},
								{
									"key": "status",
									"value": "selesai",
									"type": "text"
								}
							]
						},
						"url": {
							"raw": "http://127.0.0.1:8000/api/enrollment",
							"protocol": "http",
							"host": [
								"127",
								"0",
								"0",
								"1"
							],
							"port": "8000",
							"path": [
								"api",
								"enrollment"
							]
						}
					},
					"response": []
				},
				{
					"name": "Update Enrollment",
					"request": {
						"auth": {
							"type": "bearer",
							"bearer": [
								{
									"key": "token",
									"value": "{{token}}",
									"type": "string"
								}
							]
						},
						"method": "PATCH",
						"header": [],
						"body": {
							"mode": "raw",
							"raw": "{\r\n    \r\n}",
							"options": {
								"raw": {
									"language": "json"
								}
							}
						},
						"url": {
							"raw": "http://127.0.0.1:8000/api/enrollment/",
							"protocol": "http",
							"host": [
								"127",
								"0",
								"0",
								"1"
							],
							"port": "8000",
							"path": [
								"api",
								"enrollment",
								""
							]
						}
					},
					"response": []
				},
				{
					"name": "Hapus Enrollment",
					"request": {
						"auth": {
							"type": "bearer",
							"bearer": [
								{
									"key": "token",
									"value": "{{token}}",
									"type": "string"
								}
							]
						},
						"method": "DELETE",
						"header": [],
						"url": {
							"raw": "http://127.0.0.1:8000/api/enrollment/",
							"protocol": "http",
							"host": [
								"127",
								"0",
								"0",
								"1"
							],
							"port": "8000",
							"path": [
								"api",
								"enrollment",
								""
							]
						}
					},
					"response": []
				}
			]
		},
		{
			"name": "Lecturers",
			"item": [
				{
					"name": "Get Lecturers",
					"request": {
						"auth": {
							"type": "bearer",
							"bearer": [
								{
									"key": "token",
									"value": "{{token}}",
									"type": "string"
								}
							]
						},
						"method": "GET",
						"header": [],
						"url": {
							"raw": "http://127.0.0.1:8000/api/lecturers",
							"protocol": "http",
							"host": [
								"127",
								"0",
								"0",
								"1"
							],
							"port": "8000",
							"path": [
								"api",
								"lecturers"
							]
						}
					},
					"response": []
				},
				{
					"name": "Get Lecturers By Id",
					"request": {
						"auth": {
							"type": "bearer",
							"bearer": [
								{
									"key": "token",
									"value": "{{token}}",
									"type": "string"
								}
							]
						},
						"method": "GET",
						"header": [],
						"url": {
							"raw": "http://127.0.0.1:8000/api/lecturers/",
							"protocol": "http",
							"host": [
								"127",
								"0",
								"0",
								"1"
							],
							"port": "8000",
							"path": [
								"api",
								"lecturers",
								""
							]
						}
					},
					"response": []
				},
				{
					"name": "Create Lecturers",
					"request": {
						"auth": {
							"type": "bearer",
							"bearer": [
								{
									"key": "token",
									"value": "{{token}}",
									"type": "string"
								}
							]
						},
						"method": "POST",
						"header": [
							{
								"key": "Accept",
								"value": "application/json",
								"type": "text"
							},
							{
								"key": "Content-Type",
								"value": "application/json",
								"type": "text"
							}
						],
						"body": {
							"mode": "formdata",
							"formdata": [
								{
									"key": "name",
									"value": "",
									"type": "text"
								},
								{
									"key": "NIP",
									"value": "",
									"type": "text"
								},
								{
									"key": "department",
									"value": "",
									"type": "text"
								},
								{
									"key": "email",
									"value": "",
									"type": "text"
								}
							]
						},
						"url": {
							"raw": "http://127.0.0.1:8000/api/lecturers",
							"protocol": "http",
							"host": [
								"127",
								"0",
								"0",
								"1"
							],
							"port": "8000",
							"path": [
								"api",
								"lecturers"
							]
						}
					},
					"response": []
				},
				{
					"name": "Update Lecturers",
					"request": {
						"auth": {
							"type": "bearer",
							"bearer": [
								{
									"key": "token",
									"value": "{{token}}",
									"type": "string"
								}
							]
						},
						"method": "PATCH",
						"header": [],
						"body": {
							"mode": "raw",
							"raw": "{\r\n    \r\n}",
							"options": {
								"raw": {
									"language": "json"
								}
							}
						},
						"url": {
							"raw": "http://127.0.0.1:8000/api/lecturers/",
							"protocol": "http",
							"host": [
								"127",
								"0",
								"0",
								"1"
							],
							"port": "8000",
							"path": [
								"api",
								"lecturers",
								""
							]
						}
					},
					"response": []
				},
				{
					"name": "Hapus Lecturers",
					"request": {
						"auth": {
							"type": "bearer",
							"bearer": [
								{
									"key": "token",
									"value": "{{token}}",
									"type": "string"
								}
							]
						},
						"method": "DELETE",
						"header": [],
						"url": {
							"raw": "http://127.0.0.1:8000/api/lecturers/",
							"protocol": "http",
							"host": [
								"127",
								"0",
								"0",
								"1"
							],
							"port": "8000",
							"path": [
								"api",
								"lecturers",
								""
							]
						}
					},
					"response": []
				}
			]
		},
		{
			"name": "Course_Lecturers",
			"item": [
				{
					"name": "Get Course_Lecturers",
					"request": {
						"auth": {
							"type": "bearer",
							"bearer": [
								{
									"key": "token",
									"value": "{{token}}",
									"type": "string"
								}
							]
						},
						"method": "GET",
						"header": [],
						"url": {
							"raw": "http://127.0.0.1:8000/api/course_lecturers",
							"protocol": "http",
							"host": [
								"127",
								"0",
								"0",
								"1"
							],
							"port": "8000",
							"path": [
								"api",
								"course_lecturers"
							]
						}
					},
					"response": []
				},
				{
					"name": "Get Course_Lecturers By Id",
					"request": {
						"auth": {
							"type": "bearer",
							"bearer": [
								{
									"key": "token",
									"value": "{{token}}",
									"type": "string"
								}
							]
						},
						"method": "GET",
						"header": [],
						"url": {
							"raw": "http://127.0.0.1:8000/api/course_lecturers/",
							"protocol": "http",
							"host": [
								"127",
								"0",
								"0",
								"1"
							],
							"port": "8000",
							"path": [
								"api",
								"course_lecturers",
								""
							]
						}
					},
					"response": []
				},
				{
					"name": "Create Course_Lecturers",
					"request": {
						"auth": {
							"type": "bearer",
							"bearer": [
								{
									"key": "token",
									"value": "{{token}}",
									"type": "string"
								}
							]
						},
						"method": "POST",
						"header": [
							{
								"key": "Accept",
								"value": "application/json",
								"type": "text"
							}
						],
						"body": {
							"mode": "formdata",
							"formdata": [
								{
									"key": "course_id",
									"value": "01K0TKS1CTVS0ZNM5H3N5AMPN7",
									"type": "text"
								},
								{
									"key": "lecturer_id",
									"value": "01K0TMFBC5G505X95NZKM2KB1H",
									"type": "text"
								},
								{
									"key": "role",
									"value": "fsfds",
									"type": "text"
								}
							]
						},
						"url": {
							"raw": "http://127.0.0.1:8000/api/course_lecturers",
							"protocol": "http",
							"host": [
								"127",
								"0",
								"0",
								"1"
							],
							"port": "8000",
							"path": [
								"api",
								"course_lecturers"
							]
						}
					},
					"response": []
				},
				{
					"name": "Update Course_Lecturers",
					"request": {
						"auth": {
							"type": "bearer",
							"bearer": [
								{
									"key": "token",
									"value": "{{token}}",
									"type": "string"
								}
							]
						},
						"method": "PATCH",
						"header": [],
						"body": {
							"mode": "raw",
							"raw": "",
							"options": {
								"raw": {
									"language": "json"
								}
							}
						},
						"url": {
							"raw": "http://127.0.0.1:8000/api/course_lecturers/",
							"protocol": "http",
							"host": [
								"127",
								"0",
								"0",
								"1"
							],
							"port": "8000",
							"path": [
								"api",
								"course_lecturers",
								""
							]
						}
					},
					"response": []
				},
				{
					"name": "Hapus Course_Lecturers",
					"request": {
						"auth": {
							"type": "bearer",
							"bearer": [
								{
									"key": "token",
									"value": "{{token}}",
									"type": "string"
								}
							]
						},
						"method": "DELETE",
						"header": [],
						"url": {
							"raw": "http://127.0.0.1:8000/api/course_lecturers/",
							"protocol": "http",
							"host": [
								"127",
								"0",
								"0",
								"1"
							],
							"port": "8000",
							"path": [
								"api",
								"course_lecturers",
								""
							]
						}
					},
					"response": []
				}
			]
		},
		{
			"name": "Get Token",
			"request": {
				"auth": {
					"type": "bearer",
					"bearer": [
						{
							"key": "token",
							"value": "{{token}}",
							"type": "string"
						}
					]
				},
				"method": "POST",
				"header": [
					{
						"key": "Accept",
						"value": "application/json",
						"type": "text"
					}
				],
				"body": {
					"mode": "formdata",
					"formdata": [
						{
							"key": "username",
							"value": "anggi",
							"type": "text"
						},
						{
							"key": "password",
							"value": "password",
							"type": "text"
						}
					]
				},
				"url": {
					"raw": "http://127.0.0.1:8000/api/login",
					"protocol": "http",
					"host": [
						"127",
						"0",
						"0",
						"1"
					],
					"port": "8000",
					"path": [
						"api",
						"login"
					]
				}
			},
			"response": []
		},
		{
			"name": "Get Logout",
			"request": {
				"auth": {
					"type": "bearer",
					"bearer": [
						{
							"key": "token",
							"value": "{{token}}",
							"type": "string"
						}
					]
				},
				"method": "POST",
				"header": [],
				"url": {
					"raw": "http://127.0.0.1:8000/api/logout",
					"protocol": "http",
					"host": [
						"127",
						"0",
						"0",
						"1"
					],
					"port": "8000",
					"path": [
						"api",
						"logout"
					]
				}
			},
			"response": []
		}
	],
	"event": [
		{
			"listen": "prerequest",
			"script": {
				"type": "text/javascript",
				"packages": {},
				"exec": [
					""
				]
			}
		},
		{
			"listen": "test",
			"script": {
				"type": "text/javascript",
				"packages": {},
				"exec": [
					""
				]
			}
		}
	],
	"variable": [
		{
			"key": "token",
			"value": "1|LBKYTweUWuzCR9vu4SwHRmIqBIL6zuR7Y2oqd4jIfc4f86ed",
			"type": "string"
		}
	]
}